PyTing/__init__.py
pyting-0.0.0.dist-info/METADATA
pyting-0.0.0.dist-info/WHEEL
pyting-0.0.0.dist-info/top_level.txt
pyting-0.0.0.dist-info/RECORD
